[
  {
    "Id": 1001,
    "Name": "초보자의 낡은 철검",
    "Category": "Weapon",
    "Grade": "Common",
    "Price": 150,
    "IsTradable": true,
    "Effects": {
      "AtkBonus": 15,
      "CritChance": 0.0,
      "HpRecovery": 0
    },
    "RequiredJobs": ["Warrior", "Paladin"]
  },
  {
    "Id": 1002,
    "Name": "영혼을 가르는 자",
    "Category": "Weapon",
    "Grade": "Legendary",
    "Price": 75000,
    "IsTradable": false,
    "Effects": {
      "AtkBonus": 320,
      "CritChance": 0.15,
      "HpRecovery": 0
    },
    "RequiredJobs": ["Assassin"]
  },
  {
    "Id": 2001,
    "Name": "하급 체력 포션",
    "Category": "Consumable",
    "Grade": "Common",
    "Price": 20,
    "IsTradable": true,
    "Effects": {
      "AtkBonus": 0,
      "CritChance": 0.0,
      "HpRecovery": 50
    },
    "RequiredJobs": ["Warrior", "Paladin", "Assassin", "Mage"]
  },
  {
    "Id": 3001,
    "Name": "귀환 주문서",
    "Category": "Etc",
    "Grade": "Common",
    "Price": 100,
    "IsTradable": true,
    "Effects": {
      "AtkBonus": 0,
      "CritChance": 0.0,
      "HpRecovery": 0
    },
    "RequiredJobs": []
  }
]